fds/__init__.py
fds/sdk/__init__.py
fds/sdk/OverviewReportBuilder/__init__.py
fds/sdk/OverviewReportBuilder/api_client.py
fds/sdk/OverviewReportBuilder/configuration.py
fds/sdk/OverviewReportBuilder/exceptions.py
fds/sdk/OverviewReportBuilder/model_utils.py
fds/sdk/OverviewReportBuilder/rest.py
fds/sdk/OverviewReportBuilder/api/__init__.py
fds/sdk/OverviewReportBuilder/api/company_api.py
fds/sdk/OverviewReportBuilder/apis/__init__.py
fds/sdk/OverviewReportBuilder/model/__init__.py
fds/sdk/OverviewReportBuilder/model/error_object.py
fds/sdk/OverviewReportBuilder/model/error_object_links.py
fds/sdk/OverviewReportBuilder/model/error_object_source.py
fds/sdk/OverviewReportBuilder/model/error_response.py
fds/sdk/OverviewReportBuilder/model/key_stats_attribute_label.py
fds/sdk/OverviewReportBuilder/model/key_stats_attribute_meta.py
fds/sdk/OverviewReportBuilder/model/key_stats_attribute_meta_currency_code.py
fds/sdk/OverviewReportBuilder/model/key_stats_attribute_meta_periodicity.py
fds/sdk/OverviewReportBuilder/model/key_stats_attribute_value_number.py
fds/sdk/OverviewReportBuilder/model/key_stats_attribute_value_string.py
fds/sdk/OverviewReportBuilder/model/key_stats_data_object.py
fds/sdk/OverviewReportBuilder/model/key_stats_data_object_entity.py
fds/sdk/OverviewReportBuilder/model/key_stats_data_object_entity_active_investors.py
fds/sdk/OverviewReportBuilder/model/key_stats_data_object_entity_annual_dividend.py
fds/sdk/OverviewReportBuilder/model/key_stats_data_object_entity_average_daily_vol.py
fds/sdk/OverviewReportBuilder/model/key_stats_data_object_entity_average_daily_vol30_d.py
fds/sdk/OverviewReportBuilder/model/key_stats_data_object_entity_average_rating.py
fds/sdk/OverviewReportBuilder/model/key_stats_data_object_entity_basic_shares.py
fds/sdk/OverviewReportBuilder/model/key_stats_data_object_entity_beta.py
fds/sdk/OverviewReportBuilder/model/key_stats_data_object_entity_branches.py
fds.sdk.OverviewReportBuilder-1.2.1.dist-info/LICENSE
fds.sdk.OverviewReportBuilder-1.2.1.dist-info/METADATA
fds.sdk.OverviewReportBuilder-1.2.1.dist-info/WHEEL
fds.sdk.OverviewReportBuilder-1.2.1.dist-info/top_level.txt
fds.sdk.OverviewReportBuilder-1.2.1.dist-info/RECORD
